configprops/__init__.py
configprops-1.5.1.dist-info/LICENSE
configprops-1.5.1.dist-info/WHEEL
configprops-1.5.1.dist-info/METADATA
configprops-1.5.1.dist-info/RECORD
