Metadata-Version: 2.1
Name: configprops
Version: 1.5.1
Summary: This package provides a configuration base class to be extended with list of KEYS (same prefix) that could be overridden by environment variables.
Home-page: https://github.com/tommyxu/configprops
License: MIT
Author: Xu Yijun
Author-email: xuyijun@gmail.com
Requires-Python: >=3.7,<4.0
Classifier: License :: OSI Approved :: MIT License
Classifier: Operating System :: OS Independent
Classifier: Programming Language :: Python :: 3
Classifier: Programming Language :: Python :: 3.7
Classifier: Programming Language :: Python :: 3.8
Classifier: Programming Language :: Python :: 3.9
Requires-Dist: prettytable (>=2.1.0,<3.0.0)
Requires-Dist: python-dotenv (>=0.15.0,<0.16.0)
Project-URL: Repository, https://github.com/tommyxu/configprops
